mailie/__init__.py
mailie/__version__.py
mailie/_configuration.py
mailie/_email.py
mailie/_policy.py
mailie/commands/__init__.py
mailie/commands/attach.py
mailie/commands/headers.py
mailie/commands/send.py
mailie/mailie.py
mailie-0.1.0.dist-info/entry_points.txt
mailie-0.1.0.dist-info/LICENSE
mailie-0.1.0.dist-info/WHEEL
mailie-0.1.0.dist-info/METADATA
mailie-0.1.0.dist-info/RECORD
