Metadata-Version: 2.1
Name: mailie
Version: 0.1.0
Summary: A Python email DSL and CLI with asynchronous sending capabilities.
Author: symonk
Author-email: jackofspaces@gmail.com
Requires-Python: >=3.8,<4.0
Classifier: Programming Language :: Python :: 3
Classifier: Programming Language :: Python :: 3.10
Classifier: Programming Language :: Python :: 3.8
Classifier: Programming Language :: Python :: 3.9
Requires-Dist: aiosmtplib (>=1.1.6,<2.0.0)
Requires-Dist: colorama (>=0.4.4,<0.5.0)
Requires-Dist: typer (>=0.4.0,<0.5.0)
